littlelee_naver_news_crawler/__init__.py
littlelee_naver_news_crawler/server.py
littlelee_naver_news_crawler-0.1.0.dist-info/METADATA
littlelee_naver_news_crawler-0.1.0.dist-info/WHEEL
littlelee_naver_news_crawler-0.1.0.dist-info/entry_points.txt
littlelee_naver_news_crawler-0.1.0.dist-info/RECORD
